scan_tagger/__init__.py
scan_tagger-0.1.0.dist-info/LICENSE
scan_tagger-0.1.0.dist-info/METADATA
scan_tagger-0.1.0.dist-info/WHEEL
scan_tagger-0.1.0.dist-info/entry_points.txt
scan_tagger-0.1.0.dist-info/top_level.txt
scan_tagger-0.1.0.dist-info/RECORD
