Metadata-Version: 2.1
Name: scan_tagger
Version: 0.1.0
Summary: A helper script for applying metadata from Exif Notes to scans.
Home-page: https://github.com/xiongchiamiov/scan-tagger
Author: James Pearson Hughes
Author-email: pearson@changedmy.name
License: UNKNOWN
Project-URL: Bug Tracker, https://github.com/xiongchiamiov/scan-tagger/issues
Platform: UNKNOWN
Classifier: Programming Language :: Python :: 3
Classifier: License :: OSI Approved :: MIT License
Classifier: Operating System :: OS Independent
Requires-Python: >=3.6
License-File: LICENSE
